{
    "client": "Thunder Client",
    "collectionName": "Visitech",
    "dateExported": "2024-08-09T13:18:47.867Z",
    "version": "1.1",
    "folders": [
        {
            "_id": "196f953a-a22e-4ec0-a91e-ce841c1081aa",
            "name": "Auth",
            "containerId": "",
            "created": "2024-08-02T08:04:12.605Z",
            "sortNum": 10000
        },
        {
            "_id": "b7c4e3d1-bc99-4ff0-b0f7-5ceea7a0fa43",
            "name": "Users",
            "containerId": "",
            "created": "2024-08-02T08:08:24.160Z",
            "sortNum": 20000
        },
        {
            "_id": "9692091c-141e-412a-89f9-ed82cc2730dc",
            "name": "Doctors",
            "containerId": "",
            "created": "2024-08-02T08:11:44.982Z",
            "sortNum": 30000
        },
        {
            "_id": "4b95f9ac-0d15-4ad5-8255-98879bb69224",
            "name": "Expertises",
            "containerId": "",
            "created": "2024-08-02T09:13:25.563Z",
            "sortNum": 40000
        },
        {
            "_id": "dbd981a7-cab2-40fd-91b0-a52a0ee27671",
            "name": "Reviews",
            "containerId": "",
            "created": "2024-08-04T19:12:57.502Z",
            "sortNum": 50000
        }
    ],
    "requests": [
        {
            "_id": "7d624e39-1472-4d02-828f-66808d8b5258",
            "colId": "86f44b4a-c548-46ad-a088-82eb55a008d1",
            "containerId": "b7c4e3d1-bc99-4ff0-b0f7-5ceea7a0fa43",
            "name": "http://127.0.0.1:8000/api/whoami",
            "url": "http://127.0.0.1:8000/api/whoami",
            "method": "GET",
            "sortNum": 10000,
            "created": "2024-08-02T07:24:37.051Z",
            "modified": "2024-08-02T16:12:08.924Z",
            "headers": [
                {
                    "name": "Accept",
                    "value": "application/json"
                },
                {
                    "name": "User-Agent",
                    "value": "Thunder Client (https://www.thunderclient.com)",
                    "isDisabled": true
                }
            ],
            "params": [
                {
                    "name": "نیاز به توکن",
                    "value": "",
                    "isDisabled": true,
                    "isPath": false
                }
            ],
            "auth": {
                "type": "bearer",
                "bearer": "نیاز به توکن"
            },
            "tests": []
        },
        {
            "_id": "4c0c4794-d5d8-4d56-96a8-e70c666d8530",
            "colId": "86f44b4a-c548-46ad-a088-82eb55a008d1",
            "containerId": "196f953a-a22e-4ec0-a91e-ce841c1081aa",
            "name": "auth/sendCode",
            "url": "http://127.0.0.1:8000/api/auth/sendCode?phone=09901988088",
            "method": "POST",
            "sortNum": 10000,
            "created": "2024-08-02T07:24:37.052Z",
            "modified": "2024-08-08T18:43:39.234Z",
            "headers": [],
            "params": [
                {
                    "name": "phone",
                    "value": "09901988088",
                    "isPath": false
                }
            ],
            "tests": []
        },
        {
            "_id": "3c03f8c0-00d2-4a90-a00d-ff1661ab7860",
            "colId": "86f44b4a-c548-46ad-a088-82eb55a008d1",
            "containerId": "196f953a-a22e-4ec0-a91e-ce841c1081aa",
            "name": "auth/checkCode",
            "url": "http://127.0.0.1:8000/api/auth/checkCode?phone=09901988088&code=4729",
            "method": "POST",
            "sortNum": 15000,
            "created": "2024-08-02T08:19:22.854Z",
            "modified": "2024-08-08T18:44:09.243Z",
            "headers": [],
            "params": [
                {
                    "name": "phone",
                    "value": "09901988088",
                    "isPath": false
                },
                {
                    "name": "code",
                    "value": "4729",
                    "isPath": false
                }
            ],
            "tests": []
        },
        {
            "_id": "2b9ebc08-39c5-4158-a228-ab843933ae19",
            "colId": "86f44b4a-c548-46ad-a088-82eb55a008d1",
            "containerId": "196f953a-a22e-4ec0-a91e-ce841c1081aa",
            "name": "auth/checkPassword",
            "url": "http://127.0.0.1:8000/api/auth/checkPassword?phone=09901988088&password=Hn13801380",
            "method": "POST",
            "sortNum": 20000,
            "created": "2024-08-02T07:24:37.049Z",
            "modified": "2024-08-08T18:44:27.092Z",
            "headers": [
                {
                    "name": "Accept",
                    "value": "application/json"
                },
                {
                    "name": "User-Agent",
                    "value": "Thunder Client (https://www.thunderclient.com)",
                    "isDisabled": true
                }
            ],
            "params": [
                {
                    "name": "phone",
                    "value": "09901988088",
                    "isPath": false
                },
                {
                    "name": "password",
                    "value": "Hn13801380",
                    "isPath": false
                }
            ],
            "auth": {
                "type": "bearer",
                "bearer": "7|C7JQonjp3RMEvzHGgFD7CK58L3ZpnQbcssBIUykc57d43671"
            },
            "tests": []
        },
        {
            "_id": "16ff21b0-45ea-4ea0-9b6a-e9a00e3d977d",
            "colId": "86f44b4a-c548-46ad-a088-82eb55a008d1",
            "containerId": "196f953a-a22e-4ec0-a91e-ce841c1081aa",
            "name": "auth/registerUser",
            "url": "http://127.0.0.1:8000/api/auth/registerUser",
            "method": "POST",
            "sortNum": 30000,
            "created": "2024-08-02T08:28:32.223Z",
            "modified": "2024-08-09T12:07:47.443Z",
            "headers": [
                {
                    "name": "Accept",
                    "value": "application/json"
                }
            ],
            "params": [],
            "body": {
                "type": "formdata",
                "raw": "",
                "form": [
                    {
                        "name": "first_name",
                        "value": "حسین"
                    },
                    {
                        "name": "last_name",
                        "value": "غلامی"
                    },
                    {
                        "name": "phone",
                        "value": "09901988088"
                    },
                    {
                        "name": "password",
                        "value": "Hn13801380"
                    },
                    {
                        "name": "national_code",
                        "value": "1363089436"
                    },
                    {
                        "name": "code",
                        "value": "4972"
                    },
                    {
                        "name": "gender",
                        "value": "0"
                    },
                    {
                        "name": "birthday",
                        "value": "1368/08/16"
                    },
                    {
                        "name": "expertise_id",
                        "value": "4"
                    },
                    {
                        "name": "date_start_treatment",
                        "value": "1372/11/05"
                    },
                    {
                        "name": "address",
                        "value": "تبریز چهارراه منصور برج ابریشم طبقه 7"
                    },
                    {
                        "name": "office_phone",
                        "value": "04137289426"
                    },
                    {
                        "name": "days_of_week",
                        "value": "1"
                    },
                    {
                        "name": "appointments_number",
                        "value": "20"
                    },
                    {
                        "name": "as_doctor",
                        "value": "true"
                    }
                ]
            },
            "tests": []
        },
        {
            "_id": "a8145722-b91a-47a6-a870-071e84984136",
            "colId": "86f44b4a-c548-46ad-a088-82eb55a008d1",
            "containerId": "196f953a-a22e-4ec0-a91e-ce841c1081aa",
            "name": "auth/logout",
            "url": "http://127.0.0.1:8000/api/auth/logout",
            "method": "POST",
            "sortNum": 40000,
            "created": "2024-08-02T08:42:31.831Z",
            "modified": "2024-08-02T08:42:31.831Z",
            "headers": [],
            "params": [
                {
                    "name": "نیاز به توکن",
                    "value": "",
                    "isDisabled": true,
                    "isPath": false
                }
            ],
            "auth": {
                "type": "bearer",
                "bearer": "توکن فعلی رو اینجا قرار بده"
            },
            "tests": []
        },
        {
            "_id": "02b5a0ef-5ac9-4d15-ab64-0a145c8ccb60",
            "colId": "86f44b4a-c548-46ad-a088-82eb55a008d1",
            "containerId": "9692091c-141e-412a-89f9-ed82cc2730dc",
            "name": "doctors",
            "url": "http://127.0.0.1:8000/api/doctors",
            "method": "GET",
            "sortNum": 50000,
            "created": "2024-08-02T08:51:26.687Z",
            "modified": "2024-08-02T11:04:23.625Z",
            "headers": [],
            "params": [],
            "tests": []
        },
        {
            "_id": "840adebe-ed11-4c65-8396-278c48a609c4",
            "colId": "86f44b4a-c548-46ad-a088-82eb55a008d1",
            "containerId": "9692091c-141e-412a-89f9-ed82cc2730dc",
            "name": "doctor/{id}",
            "url": "http://127.0.0.1:8000/api/doctors/{id}",
            "method": "GET",
            "sortNum": 60000,
            "created": "2024-08-02T09:12:45.205Z",
            "modified": "2024-08-02T11:12:36.366Z",
            "headers": [],
            "params": [
                {
                    "name": "id",
                    "value": "4",
                    "isPath": true
                }
            ],
            "tests": []
        },
        {
            "_id": "f720e08d-1422-44f7-888a-8b032e6ed07e",
            "colId": "86f44b4a-c548-46ad-a088-82eb55a008d1",
            "containerId": "dbd981a7-cab2-40fd-91b0-a52a0ee27671",
            "name": "reviews",
            "url": "http://127.0.0.1:8000/api/reviews",
            "method": "GET",
            "sortNum": 60000,
            "created": "2024-08-04T20:05:10.710Z",
            "modified": "2024-08-04T20:05:10.710Z",
            "headers": [],
            "params": [],
            "tests": []
        },
        {
            "_id": "e3c8f2a7-19bf-4685-82d0-4bd2a2727d12",
            "colId": "86f44b4a-c548-46ad-a088-82eb55a008d1",
            "containerId": "4b95f9ac-0d15-4ad5-8255-98879bb69224",
            "name": "expertises",
            "url": "http://127.0.0.1:8000/api/expertises",
            "method": "GET",
            "sortNum": 70000,
            "created": "2024-08-02T11:07:43.896Z",
            "modified": "2024-08-02T11:07:43.896Z",
            "headers": [],
            "params": [],
            "tests": []
        },
        {
            "_id": "76db85d7-b2d6-4f00-8b48-1248f39f6267",
            "colId": "86f44b4a-c548-46ad-a088-82eb55a008d1",
            "containerId": "9692091c-141e-412a-89f9-ed82cc2730dc",
            "name": "doctor/{id}",
            "url": "http://127.0.0.1:8000/api/doctors/{id}",
            "method": "DELETE",
            "sortNum": 70000,
            "created": "2024-08-02T11:12:23.985Z",
            "modified": "2024-08-02T11:12:23.985Z",
            "headers": [],
            "params": [
                {
                    "name": "id",
                    "value": "4",
                    "isPath": true
                }
            ],
            "tests": []
        },
        {
            "_id": "704407e7-c20c-4f48-bb82-303ca0c168f1",
            "colId": "86f44b4a-c548-46ad-a088-82eb55a008d1",
            "containerId": "9692091c-141e-412a-89f9-ed82cc2730dc",
            "name": "/search",
            "url": "http://127.0.0.1:8000/api/search/{name}",
            "method": "GET",
            "sortNum": 80000,
            "created": "2024-08-02T08:11:21.912Z",
            "modified": "2024-08-03T22:05:04.995Z",
            "headers": [],
            "params": [
                {
                    "name": "name",
                    "value": "ه",
                    "isPath": true
                }
            ],
            "tests": []
        },
        {
            "_id": "069d33c9-0234-42a1-aa61-0c7061a82bb8",
            "colId": "86f44b4a-c548-46ad-a088-82eb55a008d1",
            "containerId": "4b95f9ac-0d15-4ad5-8255-98879bb69224",
            "name": "expertises/{id}",
            "url": "http://127.0.0.1:8000/api/expertises/{id}",
            "method": "GET",
            "sortNum": 80000,
            "created": "2024-08-02T11:09:10.432Z",
            "modified": "2024-08-02T11:09:10.432Z",
            "headers": [],
            "params": [
                {
                    "name": "id",
                    "value": "2",
                    "isPath": true
                }
            ],
            "tests": []
        },
        {
            "_id": "d1070dab-42c1-4a6d-a4f2-c1059bc41642",
            "colId": "86f44b4a-c548-46ad-a088-82eb55a008d1",
            "containerId": "4b95f9ac-0d15-4ad5-8255-98879bb69224",
            "name": "expertises",
            "url": "http://127.0.0.1:8000/api/expertises",
            "method": "POST",
            "sortNum": 85000,
            "created": "2024-08-03T21:27:11.527Z",
            "modified": "2024-08-03T21:27:11.527Z",
            "headers": [],
            "params": [],
            "body": {
                "type": "formdata",
                "raw": "",
                "form": [
                    {
                        "name": "name",
                        "value": "مامایی"
                    },
                    {
                        "name": "slug",
                        "value": "مامایی"
                    }
                ]
            },
            "auth": {
                "type": "bearer",
                "bearer": "3|a7d2Rw5xTXNZTaKoVBQbHVOwbBoNv4m2gY4q3Zj2ebb25113"
            },
            "tests": []
        },
        {
            "_id": "9e1b7514-4652-4890-bbc4-f4bd8c9d26a7",
            "colId": "86f44b4a-c548-46ad-a088-82eb55a008d1",
            "containerId": "4b95f9ac-0d15-4ad5-8255-98879bb69224",
            "name": "expertises/{id}",
            "url": "http://127.0.0.1:8000/api/expertises/{id}",
            "method": "PUT",
            "sortNum": 87500,
            "created": "2024-08-04T18:34:40.579Z",
            "modified": "2024-08-04T18:55:42.718Z",
            "headers": [
                {
                    "name": "Accept",
                    "value": "application/json"
                },
                {
                    "name": "User-Agent",
                    "value": "Thunder Client (https://www.thunderclient.com)",
                    "isDisabled": true
                }
            ],
            "params": [
                {
                    "name": "id",
                    "value": "2",
                    "isPath": true
                }
            ],
            "body": {
                "type": "formdata",
                "raw": "",
                "form": [
                    {
                        "name": "name",
                        "value": "للللل"
                    },
                    {
                        "name": "slug",
                        "value": "مامایی"
                    }
                ]
            },
            "auth": {
                "type": "bearer",
                "bearer": "1|uAKvWlag2jMEPrxSrVoyLSJYDEK8XgSQnmUO0ZC90299c04f"
            },
            "tests": []
        },
        {
            "_id": "606b6246-871d-4228-b085-6c5efeb2c220",
            "colId": "86f44b4a-c548-46ad-a088-82eb55a008d1",
            "containerId": "4b95f9ac-0d15-4ad5-8255-98879bb69224",
            "name": "expertises/{id}",
            "url": "http://127.0.0.1:8000/api/expertises/{id}",
            "method": "DELETE",
            "sortNum": 100000,
            "created": "2024-08-04T14:57:26.060Z",
            "modified": "2024-08-04T14:57:26.061Z",
            "headers": [
                {
                    "name": "Accept",
                    "value": "application/json"
                }
            ],
            "params": [
                {
                    "name": "id",
                    "value": "6",
                    "isPath": true
                }
            ],
            "auth": {
                "type": "bearer",
                "bearer": "1|uhjXE9LaXuCVHhaBf8EKI0kZ95ABKBvFEF8mgMCh6d379a4b"
            },
            "tests": []
        },
        {
            "_id": "f93a21c0-4411-44a2-b5bd-120c99737955",
            "colId": "86f44b4a-c548-46ad-a088-82eb55a008d1",
            "containerId": "4b95f9ac-0d15-4ad5-8255-98879bb69224",
            "name": "expertise/search/{id}",
            "url": "http://127.0.0.1:8000/api/expertises/search/{id}",
            "method": "GET",
            "sortNum": 110000,
            "created": "2024-08-02T09:13:28.151Z",
            "modified": "2024-08-04T12:49:34.679Z",
            "headers": [],
            "params": [
                {
                    "name": "id",
                    "value": "2",
                    "isPath": true
                }
            ],
            "tests": []
        },
        {
            "_id": "1b45fce6-640a-4de2-875e-ca8c08c134e3",
            "colId": "86f44b4a-c548-46ad-a088-82eb55a008d1",
            "containerId": "dbd981a7-cab2-40fd-91b0-a52a0ee27671",
            "name": "reviews",
            "url": "http://127.0.0.1:8000/api/reviews",
            "method": "POST",
            "sortNum": 120000,
            "created": "2024-08-04T19:13:10.541Z",
            "modified": "2024-08-04T19:13:10.543Z",
            "headers": [],
            "params": [],
            "body": {
                "type": "formdata",
                "raw": "",
                "form": [
                    {
                        "name": "user_id",
                        "value": "6"
                    },
                    {
                        "name": "doctor_id",
                        "value": "13"
                    },
                    {
                        "name": "text",
                        "value": "سلام دکتر خیلی خوبی هستند"
                    },
                    {
                        "name": "rate",
                        "value": "4"
                    }
                ]
            },
            "auth": {
                "type": "bearer",
                "bearer": "1|uAKvWlag2jMEPrxSrVoyLSJYDEK8XgSQnmUO0ZC90299c04f"
            },
            "tests": []
        },
        {
            "_id": "d0c2feb4-ba2f-4aa9-a88f-cc3c2c2b13cd",
            "colId": "86f44b4a-c548-46ad-a088-82eb55a008d1",
            "containerId": "dbd981a7-cab2-40fd-91b0-a52a0ee27671",
            "name": "reviews/{id}",
            "url": "http://127.0.0.1:8000/api/reviews/{id}",
            "method": "GET",
            "sortNum": 125000,
            "created": "2024-08-04T20:03:34.893Z",
            "modified": "2024-08-04T20:03:34.893Z",
            "headers": [],
            "params": [
                {
                    "name": "id",
                    "value": "124",
                    "isPath": true
                }
            ],
            "auth": {
                "type": "bearer",
                "bearer": "1|uAKvWlag2jMEPrxSrVoyLSJYDEK8XgSQnmUO0ZC90299c04f"
            },
            "tests": []
        },
        {
            "_id": "df3a4a47-ce1a-4338-9d30-7f38d9a2114c",
            "colId": "86f44b4a-c548-46ad-a088-82eb55a008d1",
            "containerId": "dbd981a7-cab2-40fd-91b0-a52a0ee27671",
            "name": "reviews/{id}",
            "url": "http://127.0.0.1:8000/api/reviews/{id}",
            "method": "PUT",
            "sortNum": 130000,
            "created": "2024-08-04T19:58:57.249Z",
            "modified": "2024-08-04T19:58:57.249Z",
            "headers": [],
            "params": [
                {
                    "name": "id",
                    "value": "201",
                    "isPath": true
                }
            ],
            "body": {
                "type": "formdata",
                "raw": "",
                "form": [
                    {
                        "name": "user_id",
                        "value": "6"
                    },
                    {
                        "name": "doctor_id",
                        "value": "13"
                    },
                    {
                        "name": "text",
                        "value": "سلام دکتر خیلی خوبی هستند"
                    },
                    {
                        "name": "rate",
                        "value": "4"
                    }
                ]
            },
            "auth": {
                "type": "bearer",
                "bearer": "1|uAKvWlag2jMEPrxSrVoyLSJYDEK8XgSQnmUO0ZC90299c04f"
            },
            "tests": []
        },
        {
            "_id": "7fca5841-47a3-46f0-9780-ce5f7257d4bd",
            "colId": "86f44b4a-c548-46ad-a088-82eb55a008d1",
            "containerId": "dbd981a7-cab2-40fd-91b0-a52a0ee27671",
            "name": "reviews/{id}",
            "url": "http://127.0.0.1:8000/api/reviews/{id}",
            "method": "DELETE",
            "sortNum": 140000,
            "created": "2024-08-04T20:00:33.312Z",
            "modified": "2024-08-04T20:00:33.312Z",
            "headers": [],
            "params": [
                {
                    "name": "id",
                    "value": "201",
                    "isPath": true
                }
            ],
            "auth": {
                "type": "bearer",
                "bearer": "1|uAKvWlag2jMEPrxSrVoyLSJYDEK8XgSQnmUO0ZC90299c04f"
            },
            "tests": []
        }
    ]
}